utilitys/__init__.py
utilitys/__version__.py
utilitys/_funcparse.py
utilitys/constants.py
utilitys/fns.py
utilitys/processing.py
utilitys/shims.py
utilitys/typeoverloads.py
utilitys/widgets.py
utilitys/misc/__init__.py
utilitys/misc/actionstack.py
utilitys/misc/composition.py
utilitys/params/__init__.py
utilitys/params/parameditor.py
utilitys/params/pgregistered.py
utilitys/params/plugin.py
utilitys/params/prjparam.py
utilitys/params/procwrapper.py
utilitys/params/shortcut.py
utilitys-0.5.2.dist-info/METADATA
utilitys-0.5.2.dist-info/WHEEL
utilitys-0.5.2.dist-info/top_level.txt
utilitys-0.5.2.dist-info/RECORD
