Metadata-Version: 2.1
Name: utilitys
Version: 0.5.2
Summary: Potpourri of functionalities
Home-page: https://gitlab.com/ntjess/utilitys
Author: Nathan Jessurun
Author-email: njessurun@ufl.edu
License: MIT
Download-URL: https://gitlab.com/ntjess/utilitys
Platform: UNKNOWN
Classifier: Development Status :: 3 - Alpha
Classifier: Intended Audience :: Developers
Classifier: Topic :: Software Development :: Build Tools
Classifier: License :: OSI Approved :: MIT License
Classifier: Programming Language :: Python :: 3
Requires-Python: >=3.7.*
Requires-Dist: pyqtgraph (>=0.12.3)
Requires-Dist: tqdm
Requires-Dist: numpy
Requires-Dist: pandas
Requires-Dist: docstring-parser
Requires-Dist: ruamel.yaml
Requires-Dist: typing-extensions ; python_version < "3.8"
Provides-Extra: full
Requires-Dist: PyQt5 (>=5.13.0) ; extra == 'full'
